Metadata-Version: 2.4
Name: zoho-books-mcp
Version: 0.1.0
Summary: Connect your Zoho Books account to AI assistants like Claude Desktop through the Model Context Protocol (MCP)
Project-URL: Repository, https://github.com/kkeeling/zoho-mcp
Project-URL: Issues, https://github.com/kkeeling/zoho-mcp/issues
Project-URL: Documentation, https://github.com/kkeeling/zoho-mcp#readme
Project-URL: Changelog, https://github.com/kkeeling/zoho-mcp/blob/main/CHANGELOG.md
Author-email: Keenan Keeling <keenan@example.com>
License: MIT
License-File: LICENSE
Keywords: ai,books,claude,mcp,model-context-protocol,zoho
Classifier: Development Status :: 3 - Alpha
Classifier: Intended Audience :: Developers
Classifier: License :: OSI Approved :: MIT License
Classifier: Operating System :: OS Independent
Classifier: Programming Language :: Python :: 3
Classifier: Programming Language :: Python :: 3.9
Classifier: Programming Language :: Python :: 3.10
Classifier: Programming Language :: Python :: 3.11
Classifier: Programming Language :: Python :: 3.12
Classifier: Topic :: Office/Business :: Financial :: Accounting
Requires-Python: >=3.9
Requires-Dist: anyio>=3.7.0
Requires-Dist: click>=8.1.0
Requires-Dist: email-validator>=2.0.0
Requires-Dist: httpx>=0.25.0
Requires-Dist: mcp>=1.6.0
Requires-Dist: pydantic>=2.4.0
Requires-Dist: python-dotenv>=1.0.0
Requires-Dist: starlette>=0.27.0
Requires-Dist: structlog>=23.1.0
Requires-Dist: uvicorn>=0.23.0
Provides-Extra: dev
Requires-Dist: pytest-asyncio>=0.21.0; extra == 'dev'
Requires-Dist: pytest-cov>=4.1.0; extra == 'dev'
Requires-Dist: pytest-httpx>=0.25.0; extra == 'dev'
Requires-Dist: pytest>=7.0.0; extra == 'dev'
